gistmagic/__init__.py
gistmagic/gistmagic.py
gistmagic-0.0.2.dist-info/LICENSE
gistmagic-0.0.2.dist-info/METADATA
gistmagic-0.0.2.dist-info/WHEEL
gistmagic-0.0.2.dist-info/top_level.txt
gistmagic-0.0.2.dist-info/RECORD
