Metadata-Version: 2.1
Name: gistmagic
Version: 0.0.2
Summary: History to Gist - line magic for Ipython
Home-page: https://github.com/rbagrov/GistMagic
Author: Rostislav Bagrov
Author-email: bagrov.rostislav@gmail.com
License: MIT
Keywords: ipython gist magic
Classifier: Development Status :: 3 - Alpha
Classifier: Intended Audience :: Developers
Classifier: Topic :: Software Development :: Build Tools
Classifier: License :: OSI Approved :: MIT License
Classifier: Framework :: IPython
Classifier: Framework :: Jupyter
Classifier: Programming Language :: Python :: 3.6
Classifier: Programming Language :: Python :: 3.7
Classifier: Programming Language :: Python :: 3.8
Classifier: Programming Language :: Python :: 3.9
License-File: LICENSE
Requires-Dist: ipython (>=7)
Requires-Dist: PyGithub (>=1.46)
Requires-Dist: pyperclip (>=1.8.2)
